[
  {
    "name": "Family",
    "description": "Join the server!"
  },
  {
    "name": "Hi and Welcome!",
    "description": "Write your first message in the server"
  },
  {
    "name": "I'm liking this server",
    "description": "Write 100 messages in the server"
  },
  {
    "name": "I could write a novel",
    "description": "Write 1,000 messages in the server"
  },
  {
    "name": "I wrote a novel",
    "description": "Write 10,000 messages in the server"
  },
  {
    "name": "Child",
    "description": "Be in the server for 1 month (30 days)"
  },
  {
    "name": "Adult",
    "description": "Be in the server for 6 months (180 days)"
  },
  {
    "name": "Senior",
    "description": "Be in the server for 1 year (365 days)"
  },
  {
    "name": "Innovator",
    "description": "Come up with a feature that gets implemented"
  },
  {
    "name": "Role Chamber",
    "description": "Come up with a new role that get's implemented"
  },
  {
    "name": "White Hat",
    "description": "Solve a bug with the program"
  },
  {
    "name": "Beta Tester",
    "description": "Helped develop this bot."
  }
]